pywidgets/__init__.py
pywidgets/_functions/__init__.py
pywidgets/_functions/brushing.py
pywidgets/_functions/moving.py
pywidgets/_functions/origin.py
pywidgets/_functions/selecting.py
pywidgets/_imgcv_objects/Image_objects.py
pywidgets/_imgcv_objects/__init__.py
pywidgets/_imgcv_objects/__origin.py
pywidgets/kivy/bind_widget.py
pywidgets/kivy/binding.py
pywidgets/kivy/Img/__Img_viewers.py
pywidgets/kivy/Img/__init__.py
pywidgets/kivy/Img/__origin.py
pywidgets/kivy/Img_editor/__init__.py
pywidgets/kivy/Img_editor/__origin.py
pywidgets/kivy/Img_editor/__viewers.py
pywidgets/kivy/Img_editor/assisments.py
pywidgets/kivy/Img_editor/tecnologies.py
pywidgets/kivy/Notebook/__init__.py
pywidgets/tk/Verticle_Frame.py
pywidgets/tk/func.py
pywidgets/tk/Img/__Img_viewers.py
pywidgets/tk/Img/__init__.py
pywidgets/tk/Img/__orign.py
pywidgets/tk/Img/__side_bar_viewing.py
pywidgets/tk/Img/icons/removedbackground.png
pywidgets/tk/Img_editor/__init__.py
pywidgets/tk/Img_editor/__orgin.py
pywidgets/tk/Img_editor/__viewers.py
pywidgets/tk/Img_editor/assisments.py
pywidgets/tk/Img_editor/full_editor.py
pywidgets/tk/Img_editor/tecnologies.py
pywidgets/tk/Img_editor/text_on_img.py
pywidgets/tk/Img_editor/buttonsbar/__init__.py
pywidgets/tk/Img_editor/buttonsbar/icons/blur.png
pywidgets/tk/Img_editor/buttonsbar/icons/box_mode.png
pywidgets/tk/Img_editor/buttonsbar/icons/cancel.png
pywidgets/tk/Img_editor/buttonsbar/icons/coloring_mode.png
pywidgets/tk/Img_editor/buttonsbar/icons/control_box.png
pywidgets/tk/Img_editor/buttonsbar/icons/crop.png
pywidgets/tk/Img_editor/buttonsbar/icons/download-button.png
pywidgets/tk/Img_editor/buttonsbar/icons/editing.png
pywidgets/tk/Img_editor/buttonsbar/icons/enter_button.png
pywidgets/tk/Img_editor/buttonsbar/icons/filter.png
pywidgets/tk/Img_editor/buttonsbar/icons/filters.png
pywidgets/tk/Img_editor/buttonsbar/icons/finisish_add_back_ground.png
pywidgets/tk/Img_editor/buttonsbar/icons/makebox.png
pywidgets/tk/Img_editor/buttonsbar/icons/mask.png
pywidgets-0.0.1.dist-info/METADATA
pywidgets-0.0.1.dist-info/WHEEL
pywidgets-0.0.1.dist-info/top_level.txt
pywidgets-0.0.1.dist-info/RECORD
